pyrsult.py
pyrsult-0.1.7.dist-info/licenses/LICENSE
pyrsult-0.1.7.dist-info/METADATA
pyrsult-0.1.7.dist-info/WHEEL
pyrsult-0.1.7.dist-info/top_level.txt
pyrsult-0.1.7.dist-info/RECORD
