Metadata-Version: 2.4
Name: pyrsult
Version: 0.1.7
Summary: Python Rusty Result Library: 在Python中使用Rust风格的Result类型
Author-email: Fexcode <2734664632@qq.com>
Requires-Python: >=3.10
License-File: LICENSE
Dynamic: license-file
